haralyzer/__init__.py
haralyzer/assets.py
haralyzer/errors.py
haralyzer/http.py
haralyzer/mixins.py
haralyzer/multihar.py
haralyzer-2.4.0.dist-info/LICENSE.txt
haralyzer-2.4.0.dist-info/METADATA
haralyzer-2.4.0.dist-info/WHEEL
haralyzer-2.4.0.dist-info/top_level.txt
haralyzer-2.4.0.dist-info/RECORD
