Metadata-Version: 2.1
Name: haralyzer
Version: 2.4.0
Summary: A python framework for getting useful stuff out of HAR files
Home-page: https://github.com/haralyzer/haralyzer
Author: Justin Crown
Author-email: justincrown1@gmail.com
License: MIT
Download-URL: https://github.com/haralyzer/haralyzer/releases/latest
Project-URL: Changelog, https://github.com/haralyzer/haralyzer/blob/master/HISTORY.rst
Project-URL: Issues, https://github.com/haralyzer/haralyzer/issues
Project-URL: Releases, https://github.com/haralyzer/haralyzer/releases
Keywords: har
Platform: UNKNOWN
Classifier: Development Status :: 5 - Production/Stable
Classifier: Intended Audience :: Developers
Classifier: License :: OSI Approved :: MIT License
Classifier: Natural Language :: English
Classifier: Programming Language :: Python :: 3
Classifier: Programming Language :: Python :: 3.6
Classifier: Programming Language :: Python :: 3.7
Classifier: Programming Language :: Python :: 3.8
Classifier: Programming Language :: Python :: 3.9
Classifier: Programming Language :: Python :: 3.10
Classifier: Programming Language :: Python :: 3.11
Classifier: Programming Language :: Python :: Implementation :: PyPy
Classifier: Programming Language :: Python :: Implementation :: CPython
Requires-Python: >=3.6
